{
  "editorconfig": {
    "files": 1,
    "lines": 15
  },
  "gitattributes": {
    "files": 1,
    "lines": 25
  },
  "gitignore": {
    "files": 1,
    "lines": 101
  },
  "npmrc": {
    "files": 1,
    "lines": 36
  },
  "nvmrc": {
    "files": 1,
    "lines": 1
  },
  "prettierignore": {
    "files": 1,
    "lines": 14
  },
  "prettierrc": {
    "files": 1,
    "lines": 15
  },
  "js": {
    "files": 21,
    "lines": 9521
  },
  "py": {
    "files": 750,
    "lines": 338767
  },
  "mjs": {
    "files": 3,
    "lines": 271
  },
  "json": {
    "files": 71,
    "lines": 49772
  },
  "yaml": {
    "files": 2,
    "lines": 24987
  },
  "yml": {
    "files": 1,
    "lines": 84
  },
  "ts": {
    "files": 196,
    "lines": 26692
  },
  "tsx": {
    "files": 97,
    "lines": 14323
  },
  "html": {
    "files": 5,
    "lines": 30573
  },
  "css": {
    "files": 10,
    "lines": 2036
  },
  "gradle": {
    "files": 3,
    "lines": 105
  },
  "properties": {
    "files": 4,
    "lines": 17
  },
  "bat": {
    "files": 5,
    "lines": 67
  },
  "xml": {
    "files": 8,
    "lines": 401
  },
  "kt": {
    "files": 2,
    "lines": 53
  },
  "toml": {
    "files": 2,
    "lines": 75
  },
  "sh": {
    "files": 5,
    "lines": 202
  },
  "java": {
    "files": 2,
    "lines": 579
  },
  "cjs": {
    "files": 1,
    "lines": 6
  },
  "_date": "2026-05-28 16:33",
  "_include_docs": false
}
